etfpy/__init__.py
etfpy/analytics/__init__.py
etfpy/analytics/tabular_etf.py
etfpy/analytics/utils.py
etfpy/client/__init__.py
etfpy/client/_base_client.py
etfpy/client/_etfs_scraper.py
etfpy/client/etf_client.py
etfpy/data/etfs/etfs_list.json
etfpy/deco.py
etfpy/etf.py
etfpy/exc.py
etfpy/log.py
etfpy/scripts/__init__.py
etfpy/scripts/scrape_etfs.py
etfpy/utils.py
etfpy-1.0.20.dist-info/LICENSE
etfpy-1.0.20.dist-info/METADATA
etfpy-1.0.20.dist-info/WHEEL
etfpy-1.0.20.dist-info/RECORD
